{
  "$schema": "https://static.modelcontextprotocol.io/schemas/2025-12-11/server.schema.json",
  "name": "io.github.Burakfenerci5/actionproof",
  "title": "ActionProof",
  "description": "Tamper-proof audit trail for AI agents. Signed receipts, offline-verifiable, zero backend.",
  "version": "0.0.3",
  "websiteUrl": "https://github.com/Burakfenerci5/actionproof",
  "repository": {
    "url": "https://github.com/Burakfenerci5/actionproof",
    "source": "github"
  },
  "packages": [
    {
      "registryType": "npm",
      "registryBaseUrl": "https://registry.npmjs.org",
      "identifier": "actionproof",
      "version": "0.0.3",
      "transport": {
        "type": "stdio"
      }
    }
  ]
}
